<?xml version="1.0" encoding="UTF-8"?>
<!DOCTYPE editor_palette_item PUBLIC "-//NetBeans//Editor Palette Item 1.1//EN"
  "http://www.netbeans.org/dtds/editor-palette-item-1_1.dtd">

<editor_palette_item version="1.0">

    <class name="me.dsnet.cetriolo.integration.palette.PaletteThen" />

    <icon16 urlvalue="me/dsnet/cetriolo/resources/icons/step.png" />
    <icon32 urlvalue="me/dsnet/cetriolo/resources/icons/step32.png" />
   
    <inline-description>
       <display-name>Then</display-name>
       <tooltip><![CDATA[ Drag to the editor to add a new "Then" step  ]]></tooltip> 
    </inline-description>
               
</editor_palette_item>
